AUTHORS
LICENSE
MANIFEST.in
README.rst
requirements.txt
setup.cfg
setup.py
security_monkey/__about__.py
security_monkey/__init__.py
security_monkey/alerter.py
security_monkey/auditor.py
security_monkey/backup.py
security_monkey/constants.py
security_monkey/datastore.py
security_monkey/decorators.py
security_monkey/exceptions.py
security_monkey/jirasync.py
security_monkey/monitors.py
security_monkey/reporter.py
security_monkey/scheduler.py
security_monkey/watcher.py
security_monkey.egg-info/PKG-INFO
security_monkey.egg-info/SOURCES.txt
security_monkey.egg-info/dependency_links.txt
security_monkey.egg-info/not-zip-safe
security_monkey.egg-info/requires.txt
security_monkey.egg-info/top_level.txt
security_monkey/auditors/__init__.py
security_monkey/auditors/elb.py
security_monkey/auditors/rds_security_group.py
security_monkey/auditors/redshift.py
security_monkey/auditors/s3.py
security_monkey/auditors/security_group.py
security_monkey/auditors/ses.py
security_monkey/auditors/sns.py
security_monkey/auditors/sqs.py
security_monkey/auditors/iam/__init__.py
security_monkey/auditors/iam/iam_group.py
security_monkey/auditors/iam/iam_policy.py
security_monkey/auditors/iam/iam_role.py
security_monkey/auditors/iam/iam_ssl.py
security_monkey/auditors/iam/iam_user.py
security_monkey/auditors/iam/managed_policy.py
security_monkey/common/PolicyDiff.py
security_monkey/common/__init__.py
security_monkey/common/arn.py
security_monkey/common/jinja.py
security_monkey/common/route53.py
security_monkey/common/sts_connect.py
security_monkey/common/utils.py
security_monkey/static/web/main.dart.html_reference
security_monkey/static/web/main.dart.js
security_monkey/static/web/ui.html
security_monkey/static/web/css/bootstrap-theme.css
security_monkey/static/web/css/bootstrap-theme.css.map
security_monkey/static/web/css/bootstrap-theme.min.css
security_monkey/static/web/css/bootstrap.css
security_monkey/static/web/css/bootstrap.css.map
security_monkey/static/web/css/bootstrap.min.css
security_monkey/static/web/css/main.css
security_monkey/static/web/css/signin.css
security_monkey/static/web/fonts/glyphicons-halflings-regular.eot
security_monkey/static/web/fonts/glyphicons-halflings-regular.svg
