Metadata-Version: 1.1
Name: security-monkey
Version: 0.4.0
Summary: Security Monkey monitors policy changes and alerts on insecure configurations in an AWS account
Home-page: https://github.com/Netflix/security_monkey
Author: The security_monkey developers
Author-email: security@netflix.com
License: UNKNOWN
Platform: UNKNOWN
Classifier: Framework :: Flask
Classifier: Intended Audience :: Developers
Classifier: Intended Audience :: System Administrators
Classifier: Operating System :: OS Independent
Classifier: Topic :: Software Development
Classifier: Programming Language :: Python :: 2.7
Classifier: Natural Language :: English
Classifier: License :: OSI Approved :: Apache Software License
